pyaquael/__init__.py
pyaquael/aquael.py
pyaquael-2.0.1.dist-info/METADATA
pyaquael-2.0.1.dist-info/WHEEL
pyaquael-2.0.1.dist-info/entry_points.txt
pyaquael-2.0.1.dist-info/top_level.txt
pyaquael-2.0.1.dist-info/RECORD
