Metadata-Version: 2.2
Name: pyaquael
Version: 2.0.1
Summary: A python library for the Aquael Leddy link unofficial API
Author: Christopher Haglund
Project-URL: Homepage, https://github.com/choffah/pyaquael
Project-URL: Issues, https://github.com/choffah/pyaquael/issues
Classifier: Programming Language :: Python :: 3
Classifier: License :: OSI Approved :: BSD License
Classifier: Operating System :: OS Independent
Requires-Python: >=3.8
Requires-Dist: docopt
Requires-Dist: asyncio
Requires-Dist: asyncudp
